ffpm/__init__.py
ffpm/ffpm.py
ffpm-2.0.0.dist-info/licenses/LICENSE
ffpm-2.0.0.dist-info/METADATA
ffpm-2.0.0.dist-info/WHEEL
ffpm-2.0.0.dist-info/entry_points.txt
ffpm-2.0.0.dist-info/top_level.txt
ffpm-2.0.0.dist-info/RECORD
